Trafic_light-StateMachine-Dataflow/d_ff.v
module d_ff( input	clk, d,
             output reg q);

  	always @(posedge clk) 
      begin
    	q <= d;
   	  end

endmodule

Trafic_light-StateMachine-Dataflow/design.sv
`include "d_ff.v"

module traffic_light_dataflow( input m, clk, s0, s1, s2,
                               output r1, r2, y1, y2, g1, g2);

  wire s0_out, s1_out, s2_out; // outputs from input logic
  wire s0_dout, s1_dout, s2_dout; //outputs from register
  
// Input logic first
  assign s0_out = (~s0 && s1 && s2) || (s0 && ~s1 && ~s2 && ~m);
  assign s1_out = (~s0 && ~s1 && s2) || (~s0 && s1 && s2);
  assign s2_out = (~s0 && ~s1 && ~s2) || (~s0 && ~s1 && s2 && ~m) || (~s0 && s1 && ~s2) || (s0 && ~s1 && ~s2 && ~m);
  
// Register inputs/outouts
  d_ff inst0(.clk(clk), 
             .d(s0_out), 
             .q(s0_dout));
  
  d_ff inst1(.clk(clk), 
             .d(s1_out), 
             .q(s1_dout));
  
 d_ff inst2(.clk(clk), 
            .d(s2_out), 
            .q(s2_dout));
  
//Output logic
  
  assign r1 = (~s1_dout && s2_dout) || (~s0_dout && s2_dout);
  assign r2 = (s0_dout && ~s1_dout) || (~s0_dout && ~s1_dout);
  assign y1 = ~s1_dout && ~s2_dout && s0_dout; //can't fix this
  assign y2 = ~s0_dout && ~s1_dout && s2_dout;
  assign g1 = (~s0_dout && s1_dout && s2_dout);
  assign g2 = (~s0_dout && ~s1_dout && ~s2_dout);
    
endmodule

Trafic_light-StateMachine-Dataflow/testbench.sv
module traffic_light_dataflow_tb;
  
  reg clk;
  reg m;
  reg s0;
  reg s1; 
  reg s2;
  
  wire r1;
  wire r2;
  wire y1;
  wire y2;
  wire g1;
  wire g2;
  integer i = 0;
  
  traffic_light_dataflow uut(.clk(clk), 
                             .m(m), 
                             .s0(s0), 
                             .s1(s1), 
                             .s2(s2),
                             .r1(r1),
                             .r2(r2),
                             .y1(y1),
                             .y2(y2), 
                             .g1(g1), 
                             .g2(g2));
  

  
  initial begin
	clk = 0;
	forever #2 clk = ~clk;
  end

  
  initial begin
    
    while(i < (50)) begin
      
      {m, s0, s1, s2} = i;
      
      i = i+1;
      
      #10;
    
    end
    
    #50 $finish;
    
  end
  
 initial begin 
    $dumpfile("dump.vcd"); $dumpvars(1);
  end
  
endmodule

Trafic_light-StateMachine-Dataflow/dump.vcd
$date
	Wed Apr 21 14:47:59 2021
$end
$version
	Icarus Verilog
$end
$timescale
	1s
$end
$scope module traffic_light_dataflow_tb $end
$var wire 1 ! g1 $end
$var wire 1 " g2 $end
$var wire 1 # r1 $end
$var wire 1 $ r2 $end
$var wire 1 % y1 $end
$var wire 1 & y2 $end
$var reg 1 ' clk $end
$var integer 32 ( i [31:0] $end
$var reg 1 ) m $end
$var reg 1 * s0 $end
$var reg 1 + s1 $end
$var reg 1 , s2 $end
$upscope $end
$enddefinitions $end
#0
$dumpvars
0,
0+
0*
0)
b1 (
0'
x&
x%
x$
x#
x"
x!
$end
#2
1&
1#
1$
0!
0"
0%
1'
#4
0'
#6
1'
#8
0'
#10
1'
b10 (
1,
#12
0'
#14
0&
0$
1!
1'
#16
0'
#18
1'
#20
0'
b11 (
1+
0,
#22
1&
1$
0!
1'
#24
0'
#26
1'
#28
0'
#30
1'
b100 (
1,
#32
0'
#34
0$
0"
0#
0&
1'
#36
0'
#38
1'
#40
0'
b101 (
1*
0+
0,
#42
1$
1#
1'
#44
0'
#46
1'
#48
0'
#50
1'
b110 (
1,
#52
0'
#54
1"
0#
1$
1'
#56
0'
#58
1'
#60
0'
b111 (
1+
0,
#62
1'
#64
0'
#66
1'
#68
0'
#70
1'
b1000 (
1,
#72
0'
#74
1'
#76
0'
#78
1'
#80
0'
b1001 (
1)
0*
0+
0,
#82
0"
1#
1&
1'
#84
0'
#86
1'
#88
0'
#90
1'
b1010 (
1,
#92
0'
#94
0$
0#
0&
1'
#96
0'
#98
1'
#100
0'
b1011 (
1+
0,
#102
1&
1$
1#
1'
#104
0'
#106
1'
#108
0'
#110
1'
b1100 (
1,
#112
0'
#114
0$
0"
0#
0&
1'
#116
0'
#118
1'
#120
0'
b1101 (
1*
0+
0,
#122
1"
1$
1'
#124
0'
#126
1'
#128
0'
#130
1'
b1110 (
1,
#132
0'
#134
1'
#136
0'
#138
1'
#140
0'
b1111 (
1+
0,
#142
1'
#144
0'
#146
1'
#148
0'
#150
1'
b10000 (
1,
#152
0'
#154
1'
#156
0'
#158
1'
#160
0'
b10001 (
0)
0*
0+
0,
#162
0"
1#
1&
1'
#164
0'
#166
1'
#168
0'
#170
1'
b10010 (
1,
#172
0'
#174
0&
0$
1!
1'
#176
0'
#178
1'
#180
0'
b10011 (
1+
0,
#182
1&
1$
0!
1'
#184
0'
#186
1'
#188
0'
#190
1'
b10100 (
1,
#192
0'
#194
0$
0"
0#
0&
1'
#196
0'
#198
1'
#200
0'
b10101 (
1*
0+
0,
#202
1$
1#
1'
#204
0'
#206
1'
#208
0'
#210
1'
b10110 (
1,
#212
0'
#214
1"
0#
1$
1'
#216
0'
#218
1'
#220
0'
b10111 (
1+
0,
#222
1'
#224
0'
#226
1'
#228
0'
#230
1'
b11000 (
1,
#232
0'
#234
1'
#236
0'
#238
1'
#240
0'
b11001 (
1)
0*
0+
0,
#242
0"
1#
1&
1'
#244
0'
#246
1'
#248
0'
#250
1'
b11010 (
1,
#252
0'
#254
0$
0#
0&
1'
#256
0'
#258
1'
#260
0'
b11011 (
1+
0,
#262
1&
1$
1#
1'
#264
0'
#266
1'
#268
0'
#270
1'
b11100 (
1,
#272
0'
#274
0$
0"
0#
0&
1'
#276
0'
#278
1'
#280
0'
b11101 (
1*
0+
0,
#282
1"
1$
1'
#284
0'
#286
1'
#288
0'
#290
1'
b11110 (
1,
#292
0'
#294
1'
#296
0'
#298
1'
#300
0'
b11111 (
1+
0,
#302
1'
#304
0'
#306
1'
#308
0'
#310
1'
b100000 (
1,
#312
0'
#314
1'
#316
0'
#318
1'
#320
0'
b100001 (
0)
0*
0+
0,
#322
0"
1#
1&
1'
#324
0'
#326
1'
#328
0'
#330
1'
b100010 (
1,
#332
0'
#334
0&
0$
1!
1'
#336
0'
#338
1'
#340
0'
b100011 (
1+
0,
#342
1&
1$
0!
1'
#344
0'
#346
1'
#348
0'
#350
1'
b100100 (
1,
#352
0'
#354
0$
0"
0#
0&
1'
#356
0'
#358
1'
#360
0'
b100101 (
1*
0+
0,
#362
1$
1#
1'
#364
0'
#366
1'
#368
0'
#370
1'
b100110 (
1,
#372
0'
#374
1"
0#
1$
1'
#376
0'
#378
1'
#380
0'
b100111 (
1+
0,
#382
1'
#384
0'
#386
1'
#388
0'
#390
1'
b101000 (
1,
#392
0'
#394
1'
#396
0'
#398
1'
#400
0'
b101001 (
1)
0*
0+
0,
#402
0"
1#
1&
1'
#404
0'
#406
1'
#408
0'
#410
1'
b101010 (
1,
#412
0'
#414
0$
0#
0&
1'
#416
0'
#418
1'
#420
0'
b101011 (
1+
0,
#422
1&
1$
1#
1'
#424
0'
#426
1'
#428
0'
#430
1'
b101100 (
1,
#432
0'
#434
0$
0"
0#
0&
1'
#436
0'
#438
1'
#440
0'
b101101 (
1*
0+
0,
#442
1"
1$
1'
#444
0'
#446
1'
#448
0'
#450
1'
b101110 (
1,
#452
0'
#454
1'
#456
0'
#458
1'
#460
0'
b101111 (
1+
0,
#462
1'
#464
0'
#466
1'
#468
0'
#470
1'
b110000 (
1,
#472
0'
#474
1'
#476
0'
#478
1'
#480
0'
b110001 (
0)
0*
0+
0,
#482
0"
1#
1&
1'
#484
0'
#486
1'
#488
0'
#490
1'
b110010 (
1,
#492
0'
#494
0&
0$
1!
1'
