FIFO/design.sv

module fifo_2 (	input clk, wr_en, rd_en, rst, fifo_on,
						output empty, full,		
						input [31:0] din,
						output reg [31:0] dout
				  );

				
	reg [2:0]  count = 0;
	reg [31:0] fifo [0:7];
	reg [2:0]  write = 0;
	reg [2:0]  read = 0;


	always @(posedge clk) 
		begin
			if(fifo_on == 0);
			else 
				begin
					if(rst) 
						begin
							read = 0;
							write = 0;
					   end

			else if (rd_en == 1'b1 && count != 0) 
				begin
					dout = fifo[read];
					read = read + 1'b1; //if counter is not equal to 0 and read is enabled
				end

			else if (wr_en == 1'b1 && count < 8)
				begin
					fifo[write] = din;
					write = write + 1'b1; //if counter is less than 8 than increment the writing option
				end
			else;
		end

			if (write == 8)
					write = 0;
	
			else if(read == 8)
					read = 0;
		else;
	
			if (read > write)
				count = read- write;
	
			else if (write > read)
				count = write - read;
				else;
		end
//-----------------------------------------------------------------------------------------------------------------------//
//assigning for either a full or empty 

	assign empty = (count == 0)? 1'b1 : 1'b0;
	assign full = (count == 8)? 1'b1 : 1'b0;
	
endmodule

FIFO/testbench.sv

`timescale 1ns / 10ps

module test_fifo;

	reg clk;
	reg fifo_on;
	reg [31:0] din;
	reg rd_en;
	reg wr_en;
	reg rst;


	wire [31:0] dout;
	wire empty;
	wire full;
	

//Accessing the elements from the fifo module

	localparam period = 20; //period

	fifo_2 uut (	.clk(clk),
						.din(din),
						.wr_en(wr_en),
						.rd_en(rd_en),
						.rst(rst),
						.dout(dout),
						.empty(empty),
						.full(full),
						.fifo_on(fifo_on)
					);

	initial
		begin
	
		clk = 1'b0;
		din = 32'h0;
		rd_en = 1'b0;
		wr_en = 1'b0;
		fifo_on = 1'b0;
		rst = 1'b1;
	
	#100;
		fifo_on = 1'h1;
		rst = 1'h1;
	
	#period;
		rst = 1'h0;
		wr_en = 1'b1;
		din = 32'h0;
	
	#period;
		din = 32'h1;
	
	#period;
		din = 32'h2;
	
	#period;
		din = 32'h3;
	
	#period;
		din = 32'h4;
	
	#period;
		din = 32'h5;
	
	#period;
		wr_en = 1'b0;
		rd_en = 1'b1;
	
	#340 $finish; 
	
	end
	always #10 clk = ~clk;
 initial 
  begin
   
    	$dumpfile("dump.vcd");
    	$dumpvars(1);
    end
endmodule

FIFO/dump.vcd
$date
Wed Apr 21 10:59:19 2021
$end
$version
Riviera-PRO Version 2020.04.130.7729
$end
$timescale
10 ps
$end

$scope module test_fifo $end
$var wire 32 ! dout [31:0] $end
$var wire 1 " empty $end
$var wire 1 # full $end
$var reg 1 $ clk $end
$var reg 1 % fifo_on $end
$var reg 32 & din [31:0] $end
$var reg 1 ' rd_en $end
$var reg 1 ( wr_en $end
$var reg 1 ) rst $end
$var parameter 32 * period [31:0] $end
$upscope $end

$enddefinitions $end
$dumpvars
bx !
1"
0#
0$
0%
b0 &
0'
0(
1)
b10100 *
$end
#1000
1$
#2000
0$
#3000
1$
#4000
0$
#5000
1$
#6000
0$
#7000
1$
#8000
0$
#9000
1$
#10000
1%
0$
#11000
1$
#12000
0)
1(
0$
#13000
1$
0"
#14000
b1 &
0$
#15000
1$
#16000
b10 &
0$
#17000
1$
#18000
b11 &
0$
#19000
1$
#20000
b100 &
0$
#21000
1$
#22000
b101 &
0$
#23000
1$
#24000
0(
1'
0$
#25000
1$
b0 !
#26000
0$
#27000
1$
b1 !
#28000
0$
#29000
1$
b10 !
#30000
0$
#31000
1$
b11 !
#32000
0$
#33000
1$
b100 !
#34000
0$
#35000
1$
b101 !
#36000
0$
#37000
1$
bx !
#38000
0$
#39000
1$
#40000
0$
#41000
1$
b0 !
#42000
0$
#43000
1$
b1 !
#44000
0$
#45000
1$
b10 !
#46000
0$
#47000
1$
b11 !
#48000
0$
#49000
1$
b100 !
#50000
0$
#51000
1$
b101 !
#52000
0$
#53000
1$
bx !
#54000
0$
#55000
1$
#56000
0$
#57000
1$
b0 !
