Feedback Adder/feedback.v
module feedback( input [15:0] din,
						output [15:0] dout, 
						input	rst, 
						input	clk);

wire [15:0] a;
reg [15:0] register;

assign dout = register;
assign a = din + register;

always @(posedge clk)
begin
if (rst == 1)
register <= 0;
else 
register <= a;

end


endmodule

Feedback Adder/test.v
`timescale 1ns/100ps
module test;

reg [15:0] din; 
reg clk;
reg rst;
wire [15:0] dout;

feedback dut(.din(din),
					.dout(dout),
					.clk(clk),
					.rst(rst));
	

initial begin
$dumpvars(1, test);		
clk = 0;
rst = 1;

end

always #50 clk = ~clk;

always @(din or dout or clk ) begin
#25
rst = 0;
#26
din = 16'd20;

#51 
din = 16'd5;

#101 
din = 16'd4;
#151 
rst = 1;
#201 
din = 16'd3;
#251 
rst = 0;
#301 
din = 16'd8;

#351 $finish;

end

 
	endmodule

Feedback Adder/simulation/modelsim/dump.vcd
$date
	Tue Dec 22 16:49:14 2020
$end
$version
	ModelSim Version 10.5b
$end
$timescale
	1ps
$end

$scope module test $end
$var reg 16 ! din [15:0] $end
$var reg 1 " clk $end
$var reg 1 # rst $end
$var wire 1 $ dout [15] $end
$var wire 1 % dout [14] $end
$var wire 1 & dout [13] $end
$var wire 1 ' dout [12] $end
$var wire 1 ( dout [11] $end
$var wire 1 ) dout [10] $end
$var wire 1 * dout [9] $end
$var wire 1 + dout [8] $end
$var wire 1 , dout [7] $end
$var wire 1 - dout [6] $end
$var wire 1 . dout [5] $end
$var wire 1 / dout [4] $end
$var wire 1 0 dout [3] $end
$var wire 1 1 dout [2] $end
$var wire 1 2 dout [1] $end
$var wire 1 3 dout [0] $end
$upscope $end
$enddefinitions $end
#0
$dumpvars
bx !
0"
1#
x3
x2
x1
x0
x/
x.
x-
x,
x+
x*
x)
x(
x'
x&
x%
x$
$end
#25000
0#
#50000
1"
#51000
b10100 !
#100000
0"
#102000
b101 !
#150000
1"
#200000
0"
#203000
b100 !
#250000
1"
#300000
0"
#350000
1"
#354000
1#
#400000
0"
#450000
1"
03
02
01
00
0/
0.
0-
0,
0+
0*
0)
0(
0'
0&
0%
0$
#500000
0"
#550000
1"
#555000
b11 !
#600000
0"
#650000
1"
#700000
0"
#750000
1"
#800000
0"
#806000
0#
#850000
1"
13
12
#900000
0"
#950000
1"
03
11
#1000000
0"
#1050000
1"
13
02
01
10
#1100000
0"
#1107000
b1000 !
#1150000
1"
00
1/
#1200000
0"
#1250000
1"
10
#1300000
0"
#1350000
1"
00
0/
1.
#1400000
0"
#1450000
1"
10
