Memory 64x32/design.sv

module memory(
  output reg [32:0] data_out,
    input [7:0] address,
    input [32:0] data_in, 
    input write_enable,
    input clk
);
  reg [64:0] memory [0:32];

    always @(posedge clk) begin
        if (write_enable) begin
            memory[address] <= data_in;
        end
        	data_out <= memory[address];
    end

endmodule

Memory 64x32/testbench.sv

module memory_test;
  
  reg clk, write_enable;
  reg [32:0] data_in;
  reg [7:0] address;
  wire [32:0] data_out;
  wire [64:0] memory [0:32];
  
  memory uut (
              .clk(clk),
              .write_enable(write_enable),
              .data_in(data_in),
              .address(address),
              .data_out(data_out));
  
  initial begin
		clk = 0;
		forever #3 clk = ~clk;
	end

  
  initial #150 $finish;
  integer  i;
  initial begin  
	for(i = 0; i < 10; i = i + 1) begin
		write_enable = 1;
        #5 address = i; 
        #1 data_in = $random;
	end  
   
   for(i = 0; i < 10; i = i + 1) begin
		write_enable = 0;
        #5 address = i; 
	end  
	end
  
/*More specific addresses
	initial begin
		#5 write_enable = 0;
		#5		write_enable = 1;
     	#5 address = 8'd10; data_in = $random;
  		#5 address = 8'd22; data_in = $random;
      	#5 address = 8'd25; data_in =$random;
		#5 address = 8'd225; data_in =$random;
  		#5 address = 8'd05; data_in =$random;
		#5 address = 8'd7; data_in =$random;
  

        #5 write_enable = 0;
  		#5 address = 8'd10;
  		#5 address = 8'd22;
  		#5 address = 8'd25;
  		#5 address = 8'd225;
  		#5 address = 8'd05;
      
	#10	$finish;
	end
----------------------------------------------------*/
  initial 
  begin
   
    	$dumpfile("dump.vcd");
    	$dumpvars(1);
    end
endmodule

Memory 64x32/dump.vcd
$date
Mon Apr 26 06:17:21 2021
$end
$version
Riviera-PRO Version 2020.04.130.7729
$end
$timescale
1 ns
$end

$scope module memory_test $end
$var wire 33 ! data_out [32:0] $end
$var reg 1 " clk $end
$var reg 1 # write_enable $end
$var reg 33 $ data_in [32:0] $end
$var reg 8 % address [7:0] $end
$var integer 32 & i $end
$upscope $end

$enddefinitions $end
$dumpvars
bx !
0"
1#
bx $
bx %
b0 &
$end
#3
1"
#5
b0 %
#6
0"
b10010000101010011010100100100 $
b1 &
#9
1"
#11
b1 %
#12
0"
b111000000100010010101111010000001 $
b10 &
#15
1"
#17
b10 %
#18
0"
b110000100100001001101011000001001 $
b11 &
#21
1"
#23
b11 %
#24
0"
b110110001111100000101011001100011 $
b100 &
#27
1"
#29
b100 %
#30
0"
b110101110010111101100001101 $
b101 &
#33
1"
#35
b101 %
#36
0"
b1000110110111111001100110001101 $
b110 &
#39
1"
#41
b110 %
#42
0"
b110110010110000101000010001100101 $
b111 &
#45
1"
#47
b111 %
#48
0"
b110001001001101110101001000010010 $
b1000 &
#51
1"
#53
b1000 %
#54
0"
b111100111110001100000001 $
b1001 &
#57
1"
#59
b1001 %
#60
0"
b110110101111100110100001101 $
b0 &
0#
#63
1"
#65
b0 %
b1 &
#66
0"
#69
1"
b10010000101010011010100100100 !
#70
b1 %
b10 &
#72
0"
#75
b10 %
b11 &
1"
b110000100100001001101011000001001 !
#78
0"
#80
b11 %
b100 &
#81
1"
b110110001111100000101011001100011 !
#84
0"
#85
b100 %
b101 &
#87
1"
b110101110010111101100001101 !
#90
b101 %
b110 &
0"
#93
1"
b1000110110111111001100110001101 !
#95
b110 %
b111 &
#96
0"
#99
1"
b110110010110000101000010001100101 !
#100
b111 %
b1000 &
#102
0"
#105
b1000 %
b1001 &
1"
b111100111110001100000001 !
#108
0"
#110
b1001 %
b1010 &
#111
1"
bx !
