Parity_check-MealyMachine/dff.v
`timescale 1ns / 1ps

module dff (
	input			clk,
	input			rst,
	input			d,
	output reg	    q
	);

	always @(posedge clk or posedge rst)
		if(rst)
			q <= 1'b0;
		else
			q <= d;

endmodule

Parity_check-MealyMachine/design.sv
`include "dff.v"

`timescale 1ns / 1ps

module paritycheck_mealy (
	input		clk,
	input		rst,
	input 	x,
	output	z
	);
	
	wire		d, q;
	
	xor (d, x, q);
	
	assign z = d;

	dff DFF (
		.clk(clk),
		.rst(rst),
		.d(d),
		.q(q)
	);

endmodule

Parity_check-MealyMachine/testbench.sv
`timescale 1ns / 1ps


//`define MOORE_BEHAV
//`define MEALY
//`define MEALY_BEHAV

module paritycheck_tb;

	// Inputs
	reg clk;
	reg rst;
	reg x;

	// Outputs
	wire z;

	// Instantiate the Unit Under Test (UUT)
	/*`ifdef MOORE
		paritycheck_moore uut (
			.clk(clk), 
			.rst(rst), 
			.x(x), 
			.z(z)
		);
	`elsif MOORE_BEHAV
		paritycheck_moore_behav uut (
			.clk(clk), 
			.rst(rst), 
			.x(x), 
			.z(z)
		); */
paritycheck_mealy uut  (
			.clk(clk), 
			.rst(rst), 
			.x(x), 
			.z(z)
		);
	/*`elsif MEALY_BEHAV
		paritycheck_mealy_behav uut (
			.clk(clk), 
			.rst(rst), 
			.x(x), 
			.z(z)
		);
	`endif*/


	initial begin
		clk = 0;
		forever
			#2 clk = ~clk;
	end

	initial begin
		
		// Initialize Inputs
		rst = 1;
		x = 0;

		// Wait 5 ns for global reset to finish
		#5;
        
		// Add stimulus here
				rst = 0;
		#4		x = 1;
		#4		x = 0;
		#4		x = 1;
		#3		x = 0;
		#1		x = 1;
		#6		x = 0;
		
		#10	$stop;

	end
  
  initial begin 
    $dumpfile("dump.vcd"); $dumpvars;
  end
  
      
endmodule

Parity_check-MealyMachine/dump.vcd
$date
Wed Apr 21 10:43:15 2021
$end
$version
Riviera-PRO Version 2020.04.130.7729
$end
$timescale
1 ps
$end

$scope module paritycheck_tb $end
$var wire 1 ! z $end
$var reg 1 " clk $end
$var reg 1 # rst $end
$var reg 1 $ x $end

$scope module uut $end
$var wire 1 % clk $end
$var wire 1 & rst $end
$var wire 1 ' x $end
$var wire 1 ! z $end
$var wire 1 ( d $end
$var wire 1 ) q $end

$scope module DFF $end
$var wire 1 % clk $end
$var wire 1 & rst $end
$var wire 1 ( d $end
$var reg 1 * q $end
$upscope $end

$upscope $end

$upscope $end

$enddefinitions $end
$dumpvars
0!
0"
1#
0$
0%
1&
0'
0(
0)
0*
$end
#2000
1"
1%
#4000
0"
0%
#5000
0#
0&
#6000
1"
1%
#8000
0"
0%
#9000
1$
1'
1(
1!
#10000
1"
1%
1*
1)
0(
0!
#12000
0"
0%
#13000
0$
0'
1(
1!
#14000
1"
1%
#16000
0"
0%
#17000
1$
1'
0(
0!
#18000
1"
1%
0*
0)
1(
1!
#20000
0$
0"
0%
0'
0(
0!
#21000
1$
1'
1(
1!
#22000
1"
1%
1*
1)
0(
0!
#24000
0"
0%
#26000
1"
1%
0*
0)
1(
1!
#27000
0$
0'
0(
0!
