Half_adder/design.sv
/*---------------------------------------------------
Half adder
----------------------------------------------------*/
module half_adder (
  					input A, B,
  					output S, C
				   );
  
 //Desing logic in gate level modelinf//
  xor (S, A, B);
  and (C, A, B);
  
endmodule

Half_adder/testbench.sv
module half_adder_tb;
  
  reg A, B;
  wire S, C;
  integer i;
  
  half_adder uut (.A(A),
                  .B(B),
                  .S(S),
                  .C(C));
  
  
  initial
    begin
      
      {A, B} = 0;
      
      $monitor ("T=%0t  A=%0b , B=%0b = SUM=%0b, COUT=%0b", $time, A, B, S, C);
     
      for (i = 0; i < 10; i = i+1) begin
        #1 A <= $random;
           B <= $random;
        
      end
    end
  
  initial begin 
    $dumpfile("dump.vcd"); $dumpvars;
  end
  
endmodule

Half_adder/dump.vcd
$date
Wed Apr 21 10:33:46 2021
$end
$version
Riviera-PRO Version 2020.04.130.7729
$end
$timescale
1 ns
$end

$scope module half_adder_tb $end
$var wire 1 ! S $end
$var wire 1 " C $end
$var reg 1 # A $end
$var reg 1 $ B $end
$var integer 32 % i $end

$scope module uut $end
$var wire 1 & A $end
$var wire 1 ' B $end
$var wire 1 ! S $end
$var wire 1 " C $end
$upscope $end

$upscope $end

$enddefinitions $end
$dumpvars
0!
0"
0#
0$
b0 %
0&
0'
$end
#1
b1 %
1$
1'
1!
#2
b10 %
1#
1&
1"
0!
#3
b11 %
#4
b100 %
0$
0'
0"
1!
#5
b101 %
1$
1'
1"
0!
#6
b110 %
0#
0&
0"
1!
#7
b111 %
1#
0$
0'
1&
#8
b1000 %
#9
b1001 %
#10
b1010 %
1$
1'
1"
0!
