NOR_latch-All-ModelingStyles/testbench.sv
module rs_nor_cl_tb; // currently set for behavioral model of gated latch
  
  reg 	S;
  reg   C;
  reg 	R;
  wire	Q;
  wire	Qbar;
  
  rs_nor_cl uut (
                  .S(S),
                  .R(R),
                  .Q(Q),
                  .C(C),
                  .Qbar(Qbar));
  
  initial
    begin
       
    S = 1;
    R = 1;
      
      $monitor ("T=%0t-->    C=%0d\t S=%0d R=%0d\t Q=%0d, Qbar=%0d", $time, C, S, R, Q, Qbar);
     
    #100 S = 0;
    #100 C = 1;
      
    #100 S = 1;
    #100 R = 0;
    #100 R = 1;
    #100 C = 1;
      
    #100 S = 0;
    #100 R = 0;
    #100 C = 0;
    #100 S = 1;
         R = 1;
    #100 S = 1;
         R = 0;
      
    #100 C = 0;
    #100 S = 0;
         R = 0;
    #100 ;

    end
  
  initial begin 
    $dumpfile("dump.vcd"); $dumpvars;
  end
  
endmodule

NOR_latch-All-ModelingStyles/design.sv
/*-----------------------------------------------------------
RS NOR latch
-----------------------------------------------------------*/
module rs_nor ( input S, R,
                output Q, Qbar);
  
   nor (Q, R, Qbar);
   nor (Qbar, S, Q);
 


endmodule

/*-----------------------------------------------------------
RS NOR latch (gated latch)
-----------------------------------------------------------*/


module rs_nor_cl (  input S, R, C,
           			output reg Q, Qbar);

   always @*
     
      if(C)
        begin
         Q    <= (~R & Q) | S;
         Qbar <= (~S & Q) | R;
        end
  
  endmodule 

/*---------------------------------------------------------
Gate level representation 
-------------------------------------------------------*/
  		
 module rs_nor_cl_gate (  input  S, R, C,
          				  output Q, Qbar);
   
   wire x, y;
   
   and (x, S, C);
   and (y, R, C);
   nor (Q, x, Qbar);
   nor (Qbar, y, Q);
   
endmodule

NOR_latch-All-ModelingStyles/dump.vcd
$date
	Wed Apr 21 14:38:48 2021
$end
$version
	Icarus Verilog
$end
$timescale
	1s
$end
$scope module rs_nor $end
$var wire 1 ! Q $end
$var wire 1 " Qbar $end
$var wire 1 # R $end
$var wire 1 $ S $end
$upscope $end
$scope module rs_nor_cl_gate $end
$var wire 1 % C $end
$var wire 1 & Q $end
$var wire 1 ' Qbar $end
$var wire 1 ( R $end
$var wire 1 ) S $end
$var wire 1 * x $end
$var wire 1 + y $end
$upscope $end
$scope module rs_nor_cl_tb $end
$var wire 1 , Q $end
$var wire 1 - Qbar $end
$var reg 1 . C $end
$var reg 1 / R $end
$var reg 1 0 S $end
$scope module uut $end
$var wire 1 1 C $end
$var wire 1 2 R $end
$var wire 1 3 S $end
$var reg 1 4 Q $end
$var reg 1 5 Qbar $end
$upscope $end
$upscope $end
$enddefinitions $end
#0
$dumpvars
x5
x4
13
12
x1
10
1/
x.
x-
x,
x+
x*
z)
z(
x'
x&
z%
z$
z#
x"
x!
$end
#100
00
03
#200
15
1-
04
0,
1.
11
#300
14
1,
10
13
#400
05
0-
0/
02
#500
15
1-
1/
12
#700
04
0,
00
03
#800
05
0-
0/
02
#900
0.
01
#1000
1/
12
10
13
#1100
0/
02
#1300
00
03
