Counter/design.sv
module up_counter ( output reg [7:0] out,
  					input enable, clk, rst,
 					output valid1
                  );
  
  always @(posedge clk) begin
  	if (rst) 
    	out <= 8'b0;
  	 
  
  	else if (enable) 
   		out <= out + 1;

  end
	assign valid1 = enable; 
  
  endmodule

Counter/testbench.sv
// Code your testbench here
// or browse Examples
`timescale 1ns/1ns
module up_counter_tb;

  reg clk, rst, enable;
  wire [7:0] out;

  up_counter uut (.enable(enable),
                .clk(clk),
                .rst(rst),
                  .out(out),
                  .valid1(valid1));

	initial begin
		clk = 0;
		forever
			#2 clk = ~clk;
	end

	initial begin
		
		// Initialize Inputs
		rst = 1;
		

		// Wait 5 ns for global reset to finish
		#5;
        
		// Add stimulus here
				rst = 0;
		#5		enable = 1;
		#6		enable = 1;
		#8		enable = 1;
		#7		enable = 1;
		#2		enable = 1;
		#5		enable = 0;
		#4		enable = 0;
		#1		enable = 1;
		#9		enable = 0;
		#10	$stop;

	end
   
  initial 
  begin
   
    	$dumpfile("dump.vcd");
    	$dumpvars(1);
    end
endmodule

Counter/dump.vcd
$date
Wed Apr 21 10:53:19 2021
$end
$version
Riviera-PRO Version 2020.04.130.7729
$end
$timescale
1 ns
$end

$scope module up_counter_tb $end
$var wire 8 ! out [7:0] $end
$var wire 1 " valid1 $end
$var reg 1 # clk $end
$var reg 1 $ rst $end
$var reg 1 % enable $end
$upscope $end

$enddefinitions $end
$dumpvars
bx !
x"
0#
1$
x%
$end
#2
1#
b0 !
#4
0#
#5
0$
#6
1#
#8
0#
#10
1%
1#
1"
b1 !
#12
0#
#14
1#
b10 !
#16
0#
#18
1#
b11 !
#20
0#
#22
1#
b100 !
#24
0#
#26
1#
b101 !
#28
0#
#30
1#
b110 !
#32
0#
#34
1#
b111 !
#36
0#
#38
0%
1#
0"
#40
0#
#42
1#
#43
1%
1"
#44
0#
#46
1#
b1000 !
#48
0#
#50
1#
b1001 !
#52
0%
0#
0"
