Lamp-StateMachine-Dataflow/d_ff.sv
`timescale 1ns / 1ns

module dff(clk, rst, d, q);
  
  	input		clk, rst;
  	input		d;
	output reg	q;

  always @(posedge clk) begin
    if (rst)
      q <= 0;
    else
		q <= d;
  end

endmodule

Lamp-StateMachine-Dataflow/design.sv
`timescale 1ns / 1ns
`include "d_ff.sv"

module lamp ( input B, clk, reset,
              output L, s0, s1);
  
   wire state0;
   wire state1;
  
  // next state (input) logic
  assign state0 = B;
  assign state1 = ~s1 & s0 & ~B | s1 & B | s1 & ~s0;
  
  // output logiv
  assign L = s0 ^ s1;
  
  //state register
  dff s00   (.d(state0),
             .clk(clk),
             .rst(reset),
             .q(s0));
  
  dff s01   (.d(state1),
             .clk(clk),
             .rst(reset),
             .q(s1));
endmodule

Lamp-StateMachine-Dataflow/testbench.sv
`timescale 1ns / 1ns

module lamp_TB;
  
  reg B;
  reg clk;
  reg reset;
  
  wire L;
  wire s0;
  wire s1;
  
  lamp dut (.B(B),
            .clk(clk),
            .reset(reset),
            .L(L),
            .s0(s0),
            .s1(s1));
               
  
 	initial begin
		clk = 0;
		forever
		#3 clk = ~clk;
	end


  always #11 B = ~B;

  
  initial begin
	         reset = 1;
		     B = 0;
             
	    #7   reset = 0;

		#100	$finish;
	end
     
  initial begin 
    $dumpfile("dump.vcd"); 
    $dumpvars(1);
  end
  
endmodule

Lamp-StateMachine-Dataflow/dump.vcd
$date
	Wed Apr 21 14:47:17 2021
$end
$version
	Icarus Verilog
$end
$timescale
	1ns
$end
$scope module lamp_TB $end
$var wire 1 ! L $end
$var wire 1 " s0 $end
$var wire 1 # s1 $end
$var reg 1 $ B $end
$var reg 1 % clk $end
$var reg 1 & reset $end
$upscope $end
$enddefinitions $end
#0
$dumpvars
1&
0%
0$
x#
x"
x!
$end
#3
0!
0"
0#
1%
#6
0%
#7
0&
#9
1%
#11
1$
#12
0%
#15
1!
1"
1%
#18
0%
#21
1%
#22
0$
#24
0%
#27
0"
1#
1%
#30
0%
#33
0!
1"
1%
1$
#36
0%
#39
1%
#42
0%
#44
0$
#45
0#
0"
1%
#48
0%
#51
1%
#54
0%
#55
1$
#57
1!
1"
1%
#60
0%
#63
1%
#66
0%
0$
#69
1#
0"
1%
#72
0%
#75
1%
#77
1$
#78
0%
#81
0!
1"
1%
#84
0%
#87
1%
#88
0$
#90
0%
#93
0#
0"
1%
#96
0%
#99
1!
1"
1%
1$
