Lamp-StateMachine-Behav/design.sv
/*---------------------------------------------
State machine representing the 4 state Lamp
----------------------------------------------*/
//Behavioral model
`timescale 1ns / 1ns
module lamp_behav ( input button , clk, rst,
                      output reg L);
                     // output reg [3:0] L2);
	
  localparam S0 = 2'b00;
  localparam S1 = 2'b01; 
  localparam S2 = 2'b10; 
  localparam S3 = 2'b11;
  
  reg [1:0] state, nextstate;

  // state register
  always @(posedge clk or posedge rst) begin
      if (rst)
 		state = S0;
	else
 		state = nextstate;
  	end
  
  // transitions table
  always @(state or button) begin 
      case (state)
        S0: 
          if (button)
            nextstate = S1;
       else 
            nextstate = S0;
        
        S1: 
          if (!button) 
            nextstate = S2;
        else 
            nextstate = S1;
       
        S2: 
          if (!button)
            nextstate = S2;
        else if (button)
            nextstate = S3;
        
        S3:
          if (button)
            nextstate = S3;
          else 
            nextstate = S0;
        
        default : nextstate = S0;
        endcase
      end
  
  	// output logic
	always @(state) begin
		case(state)
			S0:
				L = 0;
			S1:
				L = 1;
            S2:
                L = 1;
            S3:
                L = 0;
		endcase
	end 
	//assign L = (state == S1  ||  state == S2);

endmodule

Lamp-StateMachine-Behav/testbench.sv
`timescale 1ns / 1ns
module lamp_behav_test;
  
  reg button;
  reg clk;
  reg rst;
  wire L;
  //wire L2;
  integer i = 0;
  
  lamp_behav uut (.button(button),
                     .clk(clk),
                     .rst(rst),
                     .L(L));
  
 	initial begin
		clk = 0;
		forever #3 clk = ~clk;
	end

  
  initial begin
    $monitor ("T=%0t  Button=%0b , rst=%0b == L=0%b, ", $time, button, rst, L);
    
    button = 0;
	#5 rst = 1;
    #5 rst = 0;
	
    repeat(5)
		#9 button = ~button;
    
    #50 $finish;
    
   end
     
  initial begin 
    $dumpfile("dump.vcd"); $dumpvars(1);
  end
  
endmodule

Lamp-StateMachine-Behav/dump.vcd
$date
	Wed Apr 21 14:59:54 2021
$end
$version
	Icarus Verilog
$end
$timescale
	1ns
$end
$scope module lamp_behav_test $end
$var wire 1 ! L $end
$var reg 1 " button $end
$var reg 1 # clk $end
$var integer 32 $ i [31:0] $end
$var reg 1 % rst $end
$upscope $end
$enddefinitions $end
#0
$dumpvars
x%
b0 $
0#
0"
x!
$end
#3
0!
1#
#5
1%
#6
0#
#9
1#
#10
0%
#12
0#
#15
1#
#18
0#
#19
1"
#21
1!
1#
#24
0#
#27
1#
#28
0"
#30
0#
#33
1#
#36
0#
#37
1"
#39
0!
1#
#42
0#
#45
1#
#46
0"
#48
0#
#51
1#
#54
0#
#55
1"
#57
1!
1#
