Shift_Register/design.sv
`timescale 1ns/1ns
//SIPO reg has been used to count 4 counter outputs.

module shift_register (
						input clk, rst,
  						input [7:0] data_in,
                        input valid_in,
  						output reg [31:0] data_out,
                        output valid_fifo
						);
  
  always @(posedge clk) begin
    
	if (rst)
    	data_out <= 32'b0;
  	else if (valid_in)
    	data_out <= {4{data_in}};
   else
     	data_out <= 32'b0;
	end

assign valid_fifo = data_out; 
  
endmodule

Shift_Register/testbench.sv
`timescale 1ns/1ns
module shift_register_tb;

  reg clk, rst, valid_in;
  reg [7:0] data_in;
  wire valid_fifo;
  wire [31:0] data_out;

  shift_register uut (.valid_in(valid_in),
                      .clk(clk),
                      .rst(rst),
                      .data_in(data_in),
                      .valid_fifo(valid_fifo),
                      .data_out(data_out));
               

	initial begin
	clk = 0;
		forever #2 clk = ~clk;
	end

	initial begin
		
		// Initialize Inputs
		rst = 1;
		

		// Wait 5 ns for global reset to finish
		#5;
        
		// Add stimulus here
				rst = 0;
		#10		valid_in = 1;
     	#12     data_in = 8'd1;
		#12     data_in = 8'd2;
      	#12     data_in = 8'd3;
      	#18     data_in = 8'd4;
      	#20		valid_in = 0;
        #22		data_in = 8'd5;
     	#24		data_in = 8'd6;
      	#26		data_in = 8'd7;
      	#28		data_in = 8'd8;
		#10	$finish;

	end
   
 initial 
  begin
   
    	$dumpfile("dump.vcd");
    	$dumpvars(1);
    end
endmodule

Shift_Register/dump.vcd
$date
Wed Apr 21 10:56:55 2021
$end
$version
Riviera-PRO Version 2020.04.130.7729
$end
$timescale
1 ns
$end

$scope module shift_register_tb $end
$var wire 1 ! valid_fifo $end
$var wire 32 " data_out [31:0] $end
$var reg 1 # clk $end
$var reg 1 $ rst $end
$var reg 1 % valid_in $end
$var reg 8 & data_in [7:0] $end
$upscope $end

$enddefinitions $end
$dumpvars
x!
bx "
0#
1$
x%
bx &
$end
#2
1#
0!
b0 "
#4
0#
#5
0$
#6
1#
#8
0#
#10
1#
#12
0#
#14
1#
#15
1%
#16
0#
#18
1#
x!
bx "
#20
0#
#22
1#
#24
0#
#26
1#
#27
b1 &
#28
0#
#30
1#
1!
b1000000010000000100000001 "
#32
0#
#34
1#
#36
0#
#38
1#
#39
b10 &
#40
0#
#42
1#
0!
b10000000100000001000000010 "
#44
0#
#46
1#
#48
0#
#50
1#
#51
b11 &
#52
0#
#54
1#
1!
b11000000110000001100000011 "
#56
0#
#58
1#
#60
0#
#62
1#
#64
0#
#66
1#
#68
0#
#69
b100 &
#70
1#
0!
b100000001000000010000000100 "
#72
0#
#74
1#
#76
0#
#78
1#
#80
0#
#82
1#
#84
0#
#86
1#
#88
0#
#89
0%
#90
1#
b0 "
#92
0#
#94
1#
#96
0#
#98
1#
#100
0#
#102
1#
#104
0#
#106
1#
#108
0#
#110
1#
#111
b101 &
#112
0#
#114
1#
#116
0#
#118
1#
#120
0#
#122
1#
#124
0#
#126
1#
#128
0#
#130
1#
#132
0#
#134
1#
#135
b110 &
#136
0#
#138
1#
#140
0#
#142
1#
#144
0#
#146
1#
#148
0#
#150
1#
#152
0#
#154
1#
#156
0#
#158
1#
#160
0#
#161
b111 &
#162
1#
#164
0#
#166
1#
#168
0#
#170
1#
#172
0#
#174
1#
#176
0#
#178
1#
#180
0#
#182
1#
#184
0#
#186
1#
#188
0#
#189
b1000 &
