Traffic_light-StateMachine/design.sv

module traffic_light_behav ( input m, clk, rst,
                             output reg r1, r2, y1, y2, g1, g2);
  
  localparam state_0 = 3'b000;
  localparam state_1 = 3'b001;
  localparam state_2 = 3'b010;
  localparam state_3 = 3'b011;
  localparam state_4 = 3'b100;
  localparam state_5 = 3'b101;

  reg [2:0] CurrentState, NextState;


  always @(posedge clk or posedge rst) begin
    if (rst) 
      CurrentState = state_0;
 	else 
      CurrentState = NextState;
   end
  
/*----------------------------------------------------------
One way to represent outputs
-----------------------------------------------------------*/
  
  always @(posedge clk) begin
    if (CurrentState == state_0) 
      begin
   		r1 = 1;
        r2 = 0;
        y1 = 0;
        y2 = 0;
        g1 = 0;
        g2 = 1;
      end
  
   else if (CurrentState == state_1) 
      begin
   		r1 = 1;
        r2 = 0;
        y1 = 0;
        y2 = 1;
        g1 = 0;
        g2 = 0;
      end
  
 else if (CurrentState == state_2) 
      begin
   		 r1 = 1;
         r2 = 1;
         y1 = 0;
         y2 = 0;
         g1 = 0;
         g2 = 0;
      end
  
 else if (CurrentState == state_3) 
      begin
         r1 = 0;
         r2 = 1;
         y1 = 0;
         y2 = 0;
   		 g1 = 1;
         g2 = 0;
         
      end
  
 else if (CurrentState == state_4) 
      begin
          r1 = 0;
          r2 = 1;
   		  y1 = 1;
          y2 = 0;
          g1 = 0;
          g2 = 0;
          
      end
  
  else if (CurrentState == state_5) 
      begin
   		 r1 = 1;
         r2 = 1;
         y1 = 0;
         y2 = 0;
         g1 = 0;
         g2 = 0;
      end
  end
  
/*--------------------------------------------------------------------
Second way to represent outputs //all outputs should get wither 1 or 0
--------------------------------------------------------------------*/ 
  
 /* always @(CurrentState) begin
		case(CurrentState)
			state_0: begin
				r1 = 1;
          		g2 = 1;
                
            end
			state_1: begin
				r1 = 1;
          		y2 = 1;
            end
            state_2: begin
                r1 = 1;
          		r2 = 1;
            end
            state_3: begin
                g1 = 1;
          		r2 = 1;
            end
          	state_4: begin
                y1 = 1;
          	    r2 = 1;
            end
            state_5: begin
                r1 = 1;
          	    r2 = 1;
            end
        endcase
	end  */
  
  
  always @(CurrentState or m) 
    begin
		NextState = CurrentState;
      	case (CurrentState)
          
	state_0 : 
		if (m) 
          NextState = state_1;
	
   state_1 : 
      if (m)
        NextState = state_3;
      else if (!m)  
        NextState = state_2;
  
   state_2: 
      if (m) 
        NextState = state_3;
    
   state_3 :
      if (m) 
        NextState = state_4;
   
   state_4 :
     if (m) 
       NextState = state_0;
     else if (!m) 
       NextState = state_5;
   
   state_5 : 
     if (m)
       NextState = state_0;
   
	endcase
	end
  
/*----------------------------------------------------------
Third  way to represent outputs 
-----------------------------------------------------------*/
  
  /* assign r1 = (CurrentState == state_0) | (CurrentState == state_1) |(CurrentState == state_2) | (CurrentState == state_5);
  assign r2 = (CurrentState == state_2) | (CurrentState == state_3) | (CurrentState == state_4) | (CurrentState == state_5);
  assign y1 = (CurrentState == state_4);
  assign y2 = (CurrentState == state_1);
  assign g1 = (CurrentState == state_3);
  assign g2 = (CurrentState == state_0);*/

endmodule

Traffic_light-StateMachine/testbench.sv

module traffic_light_behav_test;
  
  reg m;
  reg clk;
  reg rst;
  wire r1;
  wire  r2;
  wire y1;
  wire y2;
  wire g1;
  wire g2;
  integer i = 0;
  
  traffic_light_behav uut (.m(m),
                     .clk(clk),
                     .rst(rst),
                     .r1(r1),
                     .r2(r2),
                     .y1(y1),
                     .y2(y2),
                     .g1(g1),
                     .g2(g2));
                    
  
 	initial begin
		clk = 0;
		forever
		#10 clk = ~clk;
	end

  
  initial begin
   // $monitor ("T=%0t  Button=%0b , rst=%0b == L=0%b, ", $time, button, rst, L);


	#5 rst = 1;
    #5 rst = 0;
	while(i < 20) begin
      
      m = i;
      i = i+1;
      #10;
    
    end
    
    #50 $finish;
    
   end
     
  initial begin 
    $dumpfile("dump.vcd"); $dumpvars(1);
  end
  
endmodule

Traffic_light-StateMachine/dump.vcd
$date
	Wed Apr 21 14:44:43 2021
$end
$version
	Icarus Verilog
$end
$timescale
	1s
$end
$scope module traffic_light_behav_test $end
$var wire 1 ! g1 $end
$var wire 1 " g2 $end
$var wire 1 # r1 $end
$var wire 1 $ r2 $end
$var wire 1 % y1 $end
$var wire 1 & y2 $end
$var reg 1 ' clk $end
$var integer 32 ( i [31:0] $end
$var reg 1 ) m $end
$var reg 1 * rst $end
$upscope $end
$enddefinitions $end
#0
$dumpvars
x*
x)
b0 (
0'
x&
x%
x$
x#
x"
x!
$end
#5
1*
#10
1"
0!
0&
0%
0$
1#
b1 (
0)
0*
1'
#20
b10 (
1)
0'
#30
0"
1&
b11 (
0)
1'
#40
b100 (
1)
0'
#50
1!
0&
1$
0#
b101 (
0)
1'
#60
b110 (
1)
0'
#70
0!
1%
b111 (
0)
1'
#80
b1000 (
1)
0'
#90
1"
0%
0$
1#
b1001 (
0)
1'
#100
b1010 (
1)
0'
#110
0"
1&
b1011 (
0)
1'
#120
b1100 (
1)
0'
#130
1!
0&
1$
0#
b1101 (
0)
1'
#140
b1110 (
1)
0'
#150
0!
1%
b1111 (
0)
1'
#160
b10000 (
1)
0'
#170
1"
0%
0$
1#
b10001 (
0)
1'
#180
b10010 (
1)
0'
#190
0"
1&
b10011 (
0)
1'
#200
b10100 (
1)
0'
#210
1!
0&
1$
0#
1'
#220
0'
#230
0!
1%
1'
#240
0'
#250
1"
0%
0$
1#
1'
