Button_Valid-In/design.sv
`timescale 1ns/1ns

module valid_in (valid_in, clk, rst, button);
	input clk;
	input rst;
	input button;
	output [7:0] valid_in;

  	reg[7:0] valid_in;
  
always @(posedge clk)
	begin
		if(rst)
			valid_in <= 0;
		else
			valid_in <= button;
			
	end
endmodule

Button_Valid-In/testbench.sv
`timescale 1ns/1ns
module valid_in_tb;

  reg clk, rst, button;
  wire [7:0] valid_in;

  valid_in uut (.valid_in(valid_in),
                .clk(clk),
                .rst(rst),
                .button(button));

	initial begin
		clk = 0;
		forever
		#2 clk = ~clk;
	end

	initial begin
		
		// Initialize Inputs
		rst = 1;
		

		// Wait 5 ns for global reset to finish
		#5;
        
		// Add stimulus here
				rst = 0;
		#5		button = 1;
		#6		button = 0;
		#8		button = 1;
		#7		button = 0;
		#2		button = 1;
		#5		button = 0;
		#4		button = 0;
		#1		button = 1;
		#9		button = 0;
		#10	$stop;

	end
   
  initial 
  begin
   
    	$dumpfile("dump.vcd");
    	$dumpvars(1);
    end
endmodule

Button_Valid-In/dump.vcd
$date
Wed Apr 21 10:49:04 2021
$end
$version
Riviera-PRO Version 2020.04.130.7729
$end
$timescale
1 ns
$end

$scope module valid_in_tb $end
$var wire 8 ! valid_in [7:0] $end
$var reg 1 " clk $end
$var reg 1 # rst $end
$var reg 1 $ button $end
$upscope $end

$enddefinitions $end
$dumpvars
bx !
0"
1#
x$
$end
#2
1"
b0 !
#4
0"
#5
0#
#6
1"
b0x !
#8
0"
#10
1$
1"
b1 !
#12
0"
#14
1"
#16
0$
0"
#18
1"
b0 !
#20
0"
#22
1"
#24
1$
0"
#26
1"
b1 !
#28
0"
#30
1"
#31
0$
#32
0"
#33
1$
#34
1"
#36
0"
#38
0$
1"
b0 !
#40
0"
#42
1"
#43
1$
#44
0"
#46
1"
b1 !
#48
0"
#50
1"
#52
0$
0"
#54
1"
b0 !
